{
    "url": "https://cdn.shopify.com/s/files/1/2304/1219/products/B6K700R1PC-GVA_1._250x.jpg?v=1640188242",
    "key": "000034868",
    "status": "success",
    "error_message": null,
    "width": 256,
    "height": 256,
    "original_width": 250,
    "original_height": 312,
    "exif": "{\"Image Orientation\": \"Horizontal (normal)\", \"Image XResolution\": \"300\", \"Image YResolution\": \"300\", \"Image ResolutionUnit\": \"Pixels/Inch\", \"Image YCbCrPositioning\": \"Centered\", \"Image ExifOffset\": \"102\", \"EXIF ExifVersion\": \"\", \"EXIF ComponentsConfiguration\": \"\", \"EXIF FlashPixVersion\": \"\", \"EXIF ColorSpace\": \"Uncalibrated\", \"EXIF ExifImageWidth\": \"250\", \"EXIF ExifImageLength\": \"312\"}",
    "md5": "206af5ac11b53f3ab9327bfb5ee07e8d"
}