{
    "url": "https://cdn.shopify.com/s/files/1/2304/1219/products/B6U328S1PC-KBL_3.jpg?v=1647532355",
    "key": "000036824",
    "status": "success",
    "error_message": null,
    "width": 256,
    "height": 256,
    "original_width": 1500,
    "original_height": 1870,
    "exif": "{\"Image Orientation\": \"Horizontal (normal)\", \"Image XResolution\": \"120\", \"Image YResolution\": \"120\", \"Image ResolutionUnit\": \"Pixels/Inch\", \"Image YCbCrPositioning\": \"Centered\", \"Image ExifOffset\": \"102\", \"EXIF ExifVersion\": \"\", \"EXIF ComponentsConfiguration\": \"\", \"EXIF FlashPixVersion\": \"\", \"EXIF ColorSpace\": \"Uncalibrated\", \"EXIF ExifImageWidth\": \"1500\", \"EXIF ExifImageLength\": \"1870\"}",
    "md5": "74255e1b36555f3d009d3cce9f74a9aa"
}